[
  {
    "name": "Alemanha",
    "path": "./assets/images/flags/alemanha.jpg"
  },
  {
    "name": "Arábia-Saudita",
    "path": "./assets/images/flags/arabia.jpg"
  },
  {
    "name": "Argentina",
    "path": "./assets/images/flags/argentina.jpg"
  },
  {
    "name": "Austrália",
    "path": "./assets/images/flags/australia.jpg"
  },
  {
    "name": "Bélgica",
    "path": "./assets/images/flags/belgica.jpg"
  },
  {
    "name": "Brasil",
    "path": "./assets/images/flags/brasil.jpg"
  },
  {
    "name": "Camarões",
    "path": "./assets/images/flags/camaroes.jpg"
  },
  {
    "name": "Canada",
    "path": "./assets/images/flags/canada.jpg"
  },
  {
    "name": "Catar",
    "path": "./assets/images/flags/catar.jpg"
  },
  {
    "name": "Coréia do Sul",
    "path": "./assets/images/flags/skorea.jpg"
  },
  {
    "name": "Croácia",
    "path": "./assets/images/flags/croatia.jpg"
  },
  {
    "name": "Dinamarca",
    "path": "./assets/images/flags/dinamarca.jpg"
  },
  {
    "name": "Ecuador",
    "path": "./assets/images/flags/ecuador.jpg"
  },
  {
    "name": "Espanha",
    "path": "./assets/images/flags/espanha.jpg"
  },
  {
    "name": "Estados Unidos",
    "path": "./assets/images/flags/eua.jpg"
  },
  {
    "name": "França",
    "path": "./assets/images/flags/franca.jpg"
  },
  {
    "name": "Gales",
    "path": "./assets/images/flags/gales.jpg"
  },
  {
    "name": "Ghana",
    "path": "./assets/images/flags/ghana.jpg"
  },
  {
    "name": "Holanda",
    "path": "./assets/images/flags/holanda.jpg"
  },
  {
    "name": "Inglaterra",
    "path": "./assets/images/flags/inglaterra.jpg"
  },
  {
    "name": "Irã",
    "path": "./assets/images/flags/iran.jpg"
  },
  {
    "name": "Japão",
    "path": "./assets/images/flags/japao.jpg"
  },
  {
    "name": "Marrocos",
    "path": "./assets/images/flags/marrocos.jpg"
  },
  {
    "name": "México",
    "path": "./assets/images/flags/mexico.jpg"
  },
  {
    "name": "Polônia",
    "path": "./assets/images/flags/polonia.jpg"
  },
  {
    "name": "Portugal",
    "path": "./assets/images/flags/portugal.jpg"
  },
  {
    "name": "Senegal",
    "path": "./assets/images/flags/Senegal.jpg"
  },
  {
    "name": "Sérvia",
    "path": "./assets/images/flags/serbia.jpg"
  },
  {
    "name": "Suiça",
    "path": "./assets/images/flags/suica.jpg"
  },
  {
    "name": "Tunísia",
    "path": "./assets/images/flags/tunisia.jpg"
  },
  {
    "name": "Uruguai",
    "path": "./assets/images/flags/uruguai.jpg"
  }
]
